<?xml version="1.0" encoding="UTF-8" standalone="no"?>
<factura id="comprobante" version="1.1.0">
	<infoTributaria>		
		<ambiente>2</ambiente>		
		<tipoEmision>1</tipoEmision>
		<razonSocial>ROSANA GUADALUPE RODRIGUEZ JARAMILLO</razonSocial>
		<nombreComercial>SAGRADO CORAZON</nombreComercial>
		<ruc>1712759826001</ruc>
		<claveAcceso>1610201801171275982600120020010000003770001817012</claveAcceso>
		<codDoc>01</codDoc>
		<estab>002</estab>
		<ptoEmi>001</ptoEmi>
		<secuencial>000000377</secuencial>
		<dirMatriz>EPLICACHIMA S9-204 Y JAMBELI</dirMatriz>
	</infoTributaria>
	<infoFactura>
		<fechaEmision>16/10/2018</fechaEmision>
		<dirEstablecimiento>VILLA FLORA</dirEstablecimiento>
				<obligadoContabilidad>NO</obligadoContabilidad>
	
	
		<tipoIdentificacionComprador>04</tipoIdentificacionComprador>	
		<razonSocialComprador>CIRO LARCO</razonSocialComprador>
		<identificacionComprador>0100097021001</identificacionComprador>
		<direccionComprador>CAMILO EGAS  4-106 Y PASEO DE LOS CAÑARIS</direccionComprador>		
		<totalSinImpuestos>795</totalSinImpuestos>

		

		<totalDescuento>0</totalDescuento>		
		<totalConImpuestos>
						
			<totalImpuesto>				
				<codigo>2</codigo>
				<codigoPorcentaje>0</codigoPorcentaje>				
				<baseImponible>795.00</baseImponible>
				<valor>0.00</valor>
			</totalImpuesto>
						
		</totalConImpuestos>		
		<propina>0</propina>

		
		<importeTotal>795.00</importeTotal>
		<moneda>DOLAR</moneda>
				<pagos>
						<pago>
				<formaPago>20</formaPago>
				<total>795.00</total>
											</pago>
					</pagos>
			</infoFactura>
	<detalles>
				<detalle>
			<codigoPrincipal>00506</codigoPrincipal>
						<codigoAuxiliar>7019.19.0000</codigoAuxiliar>
						<descripcion>MARIA NACIMIENTO 65CMS</descripcion>
			<cantidad>2.000000</cantidad>
			<precioUnitario>80.000000</precioUnitario>
			<descuento>0.00</descuento>
			<precioTotalSinImpuesto>160</precioTotalSinImpuesto>			
			<impuestos>
								<impuesto>
					<codigo>2</codigo>
					<codigoPorcentaje>0</codigoPorcentaje>
					<tarifa>0.00</tarifa>
					<baseImponible>160</baseImponible>
					<valor>0</valor>
				</impuesto>
							</impuestos>
		</detalle>
				<detalle>
			<codigoPrincipal>00506</codigoPrincipal>
						<codigoAuxiliar>7019.19.0000</codigoAuxiliar>
						<descripcion>MARIA NACIMIENTO 65CMS</descripcion>
			<cantidad>2.000000</cantidad>
			<precioUnitario>80.000000</precioUnitario>
			<descuento>0.00</descuento>
			<precioTotalSinImpuesto>160</precioTotalSinImpuesto>			
			<impuestos>
								<impuesto>
					<codigo>2</codigo>
					<codigoPorcentaje>0</codigoPorcentaje>
					<tarifa>0.00</tarifa>
					<baseImponible>160</baseImponible>
					<valor>0</valor>
				</impuesto>
							</impuestos>
		</detalle>
				<detalle>
			<codigoPrincipal>00568</codigoPrincipal>
						<codigoAuxiliar>7019.19.0000</codigoAuxiliar>
						<descripcion>PASTOR CON OVEJA NACIMIENTO 65CMS</descripcion>
			<cantidad>1.000000</cantidad>
			<precioUnitario>80.000000</precioUnitario>
			<descuento>0.00</descuento>
			<precioTotalSinImpuesto>80</precioTotalSinImpuesto>			
			<impuestos>
								<impuesto>
					<codigo>2</codigo>
					<codigoPorcentaje>0</codigoPorcentaje>
					<tarifa>0.00</tarifa>
					<baseImponible>80</baseImponible>
					<valor>0</valor>
				</impuesto>
							</impuestos>
		</detalle>
				<detalle>
			<codigoPrincipal>00575</codigoPrincipal>
						<codigoAuxiliar>7019.19.0000</codigoAuxiliar>
						<descripcion>PASTORA CON CANTARO NACIMIENTO 65CMS</descripcion>
			<cantidad>1.000000</cantidad>
			<precioUnitario>80.000000</precioUnitario>
			<descuento>0.00</descuento>
			<precioTotalSinImpuesto>80</precioTotalSinImpuesto>			
			<impuestos>
								<impuesto>
					<codigo>2</codigo>
					<codigoPorcentaje>0</codigoPorcentaje>
					<tarifa>0.00</tarifa>
					<baseImponible>80</baseImponible>
					<valor>0</valor>
				</impuesto>
							</impuestos>
		</detalle>
				<detalle>
			<codigoPrincipal>02333</codigoPrincipal>
						<codigoAuxiliar>7019.19.0000</codigoAuxiliar>
						<descripcion>PASTORA DE GANZO</descripcion>
			<cantidad>1.000000</cantidad>
			<precioUnitario>80.000000</precioUnitario>
			<descuento>0.00</descuento>
			<precioTotalSinImpuesto>80</precioTotalSinImpuesto>			
			<impuestos>
								<impuesto>
					<codigo>2</codigo>
					<codigoPorcentaje>0</codigoPorcentaje>
					<tarifa>0.00</tarifa>
					<baseImponible>80</baseImponible>
					<valor>0</valor>
				</impuesto>
							</impuestos>
		</detalle>
				<detalle>
			<codigoPrincipal>00896</codigoPrincipal>
						<codigoAuxiliar>7019.19.0000</codigoAuxiliar>
						<descripcion>PASTOR GALLINA NACIMIENTO 65CMS</descripcion>
			<cantidad>1.000000</cantidad>
			<precioUnitario>80.000000</precioUnitario>
			<descuento>0.00</descuento>
			<precioTotalSinImpuesto>80</precioTotalSinImpuesto>			
			<impuestos>
								<impuesto>
					<codigo>2</codigo>
					<codigoPorcentaje>0</codigoPorcentaje>
					<tarifa>0.00</tarifa>
					<baseImponible>80</baseImponible>
					<valor>0</valor>
				</impuesto>
							</impuestos>
		</detalle>
				<detalle>
			<codigoPrincipal>05372</codigoPrincipal>
						<codigoAuxiliar>7019.19.0000</codigoAuxiliar>
						<descripcion>NIÑO #10 PELO LISO 50CMS</descripcion>
			<cantidad>1.000000</cantidad>
			<precioUnitario>85.000000</precioUnitario>
			<descuento>0.00</descuento>
			<precioTotalSinImpuesto>85</precioTotalSinImpuesto>			
			<impuestos>
								<impuesto>
					<codigo>2</codigo>
					<codigoPorcentaje>0</codigoPorcentaje>
					<tarifa>0.00</tarifa>
					<baseImponible>85</baseImponible>
					<valor>0</valor>
				</impuesto>
							</impuestos>
		</detalle>
				<detalle>
			<codigoPrincipal>01015</codigoPrincipal>
						<codigoAuxiliar>7019.19.0000</codigoAuxiliar>
						<descripcion>NIÑO ITALIANO</descripcion>
			<cantidad>1.000000</cantidad>
			<precioUnitario>70.000000</precioUnitario>
			<descuento>0.00</descuento>
			<precioTotalSinImpuesto>70</precioTotalSinImpuesto>			
			<impuestos>
								<impuesto>
					<codigo>2</codigo>
					<codigoPorcentaje>0</codigoPorcentaje>
					<tarifa>0.00</tarifa>
					<baseImponible>70</baseImponible>
					<valor>0</valor>
				</impuesto>
							</impuestos>
		</detalle>
			</detalles>
</factura>
