<?xml version="1.0" encoding="UTF-8" standalone="no"?>
<factura id="comprobante" version="1.1.0">
	<infoTributaria>		
		<ambiente>6</ambiente>		
		<tipoEmision>1</tipoEmision>
		<razonSocial>ROSANA GUADALUPE RODRIGUEZ JARAMILLO</razonSocial>
		<nombreComercial>SAGRADO CORAZON</nombreComercial>
		<ruc>1712759826001</ruc>
		<claveAcceso>0611201801171275982600160020010000003820001518018</claveAcceso>
		<codDoc>01</codDoc>
		<estab>002</estab>
		<ptoEmi>001</ptoEmi>
		<secuencial>000000382</secuencial>
		<dirMatriz>EPLICACHIMA S9-204 Y JAMBELI</dirMatriz>
	</infoTributaria>
	<infoFactura>
		<fechaEmision>06/11/2018</fechaEmision>
		<dirEstablecimiento>VILLA FLORA</dirEstablecimiento>
				<obligadoContabilidad>NO</obligadoContabilidad>
	
	
		<tipoIdentificacionComprador>04</tipoIdentificacionComprador>	
		<razonSocialComprador>ROSA GARCES</razonSocialComprador>
		<identificacionComprador>1802497089001</identificacionComprador>
		<direccionComprador>BELISARIO QUEVEDO</direccionComprador>		
		<totalSinImpuestos>198.8</totalSinImpuestos>

		

		<totalDescuento>0</totalDescuento>		
		<totalConImpuestos>
						
			<totalImpuesto>				
				<codigo>2</codigo>
				<codigoPorcentaje>77</codigoPorcentaje>				
				<baseImponible>198.80</baseImponible>
				<valor>0.00</valor>
			</totalImpuesto>
						
		</totalConImpuestos>		
		<propina>0</propina>

		
		<importeTotal>198.80</importeTotal>
		<moneda>DOLAR</moneda>
				<pagos>
						<pago>
				<formaPago>01</formaPago>
				<total>198.80</total>
											</pago>
					</pagos>
			</infoFactura>
	<detalles>
				<detalle>
			<codigoPrincipal>17252</codigoPrincipal>
						<codigoAuxiliar>7019.19.0000</codigoAuxiliar>
						<descripcion>JUEGO DE AVES</descripcion>
			<cantidad>1.000000</cantidad>
			<precioUnitario>16.800000</precioUnitario>
			<descuento>0.00</descuento>
			<precioTotalSinImpuesto>16.8</precioTotalSinImpuesto>			
			<impuestos>
								<impuesto>
					<codigo>2</codigo>
					<codigoPorcentaje>77</codigoPorcentaje>
					<tarifa>0.00</tarifa>
					<baseImponible>16.8</baseImponible>
					<valor>0</valor>
				</impuesto>
							</impuestos>
		</detalle>
				<detalle>
			<codigoPrincipal>00179</codigoPrincipal>
						<codigoAuxiliar>7019.19.0000</codigoAuxiliar>
						<descripcion>NIÑO #6 OJOS DE CRISTAL</descripcion>
			<cantidad>1.000000</cantidad>
			<precioUnitario>56.000000</precioUnitario>
			<descuento>0.00</descuento>
			<precioTotalSinImpuesto>56</precioTotalSinImpuesto>			
			<impuestos>
								<impuesto>
					<codigo>2</codigo>
					<codigoPorcentaje>77</codigoPorcentaje>
					<tarifa>0.00</tarifa>
					<baseImponible>56</baseImponible>
					<valor>0</valor>
				</impuesto>
							</impuestos>
		</detalle>
				<detalle>
			<codigoPrincipal>09127</codigoPrincipal>
						<codigoAuxiliar>7019.19.0000</codigoAuxiliar>
						<descripcion>NIÑO #10  CHURON 56CMS</descripcion>
			<cantidad>1.000000</cantidad>
			<precioUnitario>126.000000</precioUnitario>
			<descuento>0.00</descuento>
			<precioTotalSinImpuesto>126</precioTotalSinImpuesto>			
			<impuestos>
								<impuesto>
					<codigo>2</codigo>
					<codigoPorcentaje>77</codigoPorcentaje>
					<tarifa>0.00</tarifa>
					<baseImponible>126</baseImponible>
					<valor>0</valor>
				</impuesto>
							</impuestos>
		</detalle>
			</detalles>
</factura>
